varnishapi.py
varnishapi-60.24.dist-info/metadata.json
varnishapi-60.24.dist-info/DESCRIPTION.rst
varnishapi-60.24.dist-info/top_level.txt
varnishapi-60.24.dist-info/WHEEL
varnishapi-60.24.dist-info/METADATA
varnishapi-60.24.dist-info/RECORD
