Metadata-Version: 2.0
Name: varnishapi
Version: 60.24
Summary: Connect to libvarnish api by ctypes
Home-page: https://github.com/xcir/python-varnishapi
Author: Shohei Tanaka(@xcir)
Author-email: kokoniimasu@gmail.com
License: BSD
Keywords: varnish,varnishlog,varnishstat
Platform: any
Classifier: Development Status :: 5 - Production/Stable
Classifier: Intended Audience :: Developers
Classifier: License :: OSI Approved :: BSD License
Classifier: Natural Language :: English
Classifier: Operating System :: POSIX
Classifier: Programming Language :: Python
Classifier: Programming Language :: Python :: 3.5
Classifier: Programming Language :: Python :: 2.7
Classifier: Topic :: Internet :: WWW/HTTP
